dateh/__init__.py
dateh-0.1.0.dist-info/WHEEL
dateh-0.1.0.dist-info/METADATA
dateh-0.1.0.dist-info/RECORD
