Metadata-Version: 2.1
Name: dateh
Version: 0.1.0
Summary: h encoded date strings
License: MIT
Author: vcokltfre
Author-email: vcokltfre@gmail.com
Requires-Python: >=3.8,<4.0
Classifier: License :: OSI Approved :: MIT License
Classifier: Programming Language :: Python :: 3
Classifier: Programming Language :: Python :: 3.8
Classifier: Programming Language :: Python :: 3.9
Requires-Dist: htranslate (>=1.0.1,<2.0.0)
